pathgather/__init__.py
pathgather/client.py
pathgather/content.py
pathgather/exceptions.py
pathgather/gatherings.py
pathgather/paths.py
pathgather/providers.py
pathgather/skills.py
pathgather/types_.py
pathgather/users.py
pathgather/utils.py
pathgather/models/__init__.py
pathgather/models/content.py
pathgather/models/department.py
pathgather/models/gathering.py
pathgather/models/path.py
pathgather/models/provider.py
pathgather/models/skill.py
pathgather/models/user.py
pathgather-1.15.0.dist-info/AUTHORS.rst
pathgather-1.15.0.dist-info/LICENSE
pathgather-1.15.0.dist-info/METADATA
pathgather-1.15.0.dist-info/WHEEL
pathgather-1.15.0.dist-info/top_level.txt
pathgather-1.15.0.dist-info/RECORD
