Metadata-Version: 2.1
Name: pathgather
Version: 1.15.0
Summary: API client for PathGather
Home-page: https://github.com/tonybaloney/pathgather
Author: Anthony Shaw
Author-email: anthonyshaw@apache.org
License: Apache License (2.0)
Keywords: pathgather
Platform: UNKNOWN
Classifier: Development Status :: 5 - Production/Stable
Classifier: Environment :: Console
Classifier: Intended Audience :: Developers
Classifier: Intended Audience :: System Administrators
Classifier: License :: OSI Approved :: Apache Software License
Classifier: Operating System :: OS Independent
Classifier: Programming Language :: Python
Classifier: Topic :: Software Development :: Libraries :: Python Modules
Classifier: Programming Language :: Python :: 2.7
Classifier: Programming Language :: Python :: 3
Classifier: Programming Language :: Python :: 3.3
Classifier: Programming Language :: Python :: 3.4
Classifier: Programming Language :: Python :: 3.5
Classifier: Programming Language :: Python :: 3.6
Classifier: Programming Language :: Python :: Implementation :: CPython
Classifier: Programming Language :: Python :: Implementation :: PyPy
Requires-Dist: PyYAML
Requires-Dist: requests
Requires-Dist: attrs
Requires-Dist: arrow
